astmasrmcode/__init__.py
astmasrm-1.0.dist-info/METADATA
astmasrm-1.0.dist-info/WHEEL
astmasrm-1.0.dist-info/top_level.txt
astmasrm-1.0.dist-info/RECORD
